MANIFEST.in
README.rst
setup.py
sseclient.py
sseclient.egg-info/PKG-INFO
sseclient.egg-info/SOURCES.txt
sseclient.egg-info/dependency_links.txt
sseclient.egg-info/requires.txt
sseclient.egg-info/top_level.txt