Metadata-Version: 1.0
Name: sseclient
Version: 0.0.6
Summary: Python client library for reading Server Sent Event streams.
Home-page: http://bits.btubbs.com/sseclient
Author: Brent Tubbs
Author-email: brent.tubbs@gmail.com
License: UNKNOWN
Platform: UNKNOWN
